log2mqtt/.DS_Store
log2mqtt/__main__.py
log2mqtt-0.1.0.dist-info/LICENSE.txt
log2mqtt-0.1.0.dist-info/METADATA
log2mqtt-0.1.0.dist-info/WHEEL
log2mqtt-0.1.0.dist-info/entry_points.txt
log2mqtt-0.1.0.dist-info/RECORD
