Metadata-Version: 2.3
Name: log2mqtt
Version: 0.1.0
Summary: Pipe standard input to an MQTT server
License: MIT License
Keywords: log,logging,mqtt
Author: Harvey Lelliott
Author-email: harveylelliott@duck.com
Requires-Python: >=3.10
Classifier: Development Status :: 3 - Alpha
Classifier: Intended Audience :: Developers
Classifier: Topic :: Utilities
Classifier: Topic :: Terminals
Classifier: License :: OSI Approved :: MIT License
Classifier: Operating System :: Microsoft :: Windows :: Windows 10
Classifier: Operating System :: POSIX :: Linux
Classifier: Operating System :: MacOS :: MacOS X
Classifier: Programming Language :: Python :: 3.10
Requires-Dist: paho-mqtt (>=2.1.0,<3.0.0)
Project-URL: Homepage, https://github.com/flip-dots/log2mqtt
Project-URL: Issues, https://github.com/flip-dots/log2mqtt/issues
Project-URL: Repository, https://github.com/flip-dots/log2mqtt
